[
{"year": "2021", "name": "Stay", "info": "The Kid LAROI & Justin Bieber"},
{"year": "2021", "name": "Good 4 U", "info": "Olivia Rodrigo"},
{"year": "2021", "name": "Bad Habits", "info": "Ed Sheeran"},
{"year": "2021", "name": "Kiss Me More", "info": "Doja Cat Featuring SZA"},
{"year": "2021", "name": "Levitating", "info": "Dua Lipa"},
{"year": "2021", "name": "Take My Breath", "info": "The Weeknd"},
{"year": "2021", "name": "Butter", "info": "BTS"},
{"year": "2021", "name": "Industry Baby", "info": "Lil Nas X & Jack Harlow"},
{"year": "2021", "name": "Montero (Call Me By Your Name)", "info": "Lil Nas X"},
{"year": "2021", "name": "Deja Vu", "info": "Olivia Rodrigo"},
{"year": "2021", "name": "Save Your Tears", "info": "The Weeknd & Ariana Grande"},
{"year": "2021", "name": "Peaches", "info": "Justin Bieber Featuring Daniel Caesar & Giveon"},
{"year": "2021", "name": "Happier Than Ever", "info": "Billie Eilish"},
{"year": "2021", "name": "Leave The Door Open", "info": "Silk Sonic (Bruno Mars & Anderson .Paak)"},
{"year": "2021", "name": "Fancy Like", "info": "Walker Hayes"},
{"year": "2021", "name": "You Right", "info": "Doja Cat & The Weeknd"},
{"year": "2021", "name": "Heartbreak Anniversary", "info": "Giveon"},
{"year": "2021", "name": "Blinding Lights", "info": "The Weeknd"},
{"year": "2021", "name": "Leave Before You Love Me", "info": "Marshmello X Jonas Brothers"},
{"year": "2021", "name": "Need To Know", "info": "Doja Cat"},
{"year": "2021", "name": "Glad You Exist", "info": "Dan + Shay"},
{"year": "2021", "name": "Volvi", "info": "Aventura x Bad Bunny"},
{"year": "2021", "name": "Every Chance I Get", "info": "DJ Khaled Featuring Lil Baby & Lil Durk"},
{"year": "2021", "name": "Forever After All", "info": "Luke Combs"},
{"year": "2021", "name": "Rapstar", "info": "Polo G"},
{"year": "2021", "name": "Late At Night", "info": "Roddy Ricch"},
{"year": "2021", "name": "Lil Bit", "info": "Nelly & Florida Georgia Line"},
{"year": "2021", "name": "Without You", "info": "The Kid LAROI"},
{"year": "2021", "name": "Thot Shit", "info": "Megan Thee Stallion"},
{"year": "2021", "name": "Astronaut In The Ocean", "info": "Masked Wolf"},
{"year": "2021", "name": "Heat Waves", "info": "Glass Animals"},
{"year": "2021", "name": "Famous Friends", "info": "Chris Young + Kane Brown"},
{"year": "2021", "name": "Traitor", "info": "Olivia Rodrigo"},
{"year": "2021", "name": "Waves", "info": "Luke Bryan"},
{"year": "2021", "name": "Skate", "info": "Silk Sonic (Bruno Mars & Anderson .Paak)"},
{"year": "2021", "name": "Beautiful Mistakes", "info": "Maroon 5 Featuring Megan Thee Stallion"},
{"year": "2021", "name": "Telepatia", "info": "Kali Uchis"},
{"year": "2021", "name": "Drinkin' Beer. Talkin' God. Amen.", "info": "Chase Rice Featuring Florida Georgia Line"},
{"year": "2021", "name": "Things A Man Oughta Know", "info": "Lainey Wilson"},
{"year": "2021", "name": "Wockesha", "info": "Moneybagg Yo"},
{"year": "2021", "name": "Arcade", "info": "Duncan Laurence"},
{"year": "2021", "name": "My Ex's Best Friend", "info": "Machine Gun Kelly X blackbear"},
{"year": "2021", "name": "Country Again", "info": "Thomas Rhett"},
{"year": "2021", "name": "Essence", "info": "Wizkid Featuring Justin Bieber & Tems"},
{"year": "2021", "name": "Whole Lotta Money", "info": "BIA Featuring Nicki Minaj"},
{"year": "2021", "name": "Single Saturday Night", "info": "Cole Swindell"},
{"year": "2021", "name": "Ain't Shit", "info": "Doja Cat"},
{"year": "2021", "name": "Motley Crew", "info": "Post Malone"},
{"year": "2021", "name": "Chasing After You", "info": "Ryan Hurd With Maren Morris"},
{"year": "2021", "name": "Beggin'", "info": "Maneskin"},
{"year": "2021", "name": "If I Didn't Love You", "info": "Jason Aldean & Carrie Underwood"},
{"year": "2021", "name": "Pepas", "info": "Farruko"},
{"year": "2021", "name": "2055", "info": "Sleepy Hallow"},
{"year": "2021", "name": "Cold Beer Calling My Name", "info": "Jameson Rodgers Featuring Luke Combs"},
{"year": "2021", "name": "Permission To Dance", "info": "BTS"},
{"year": "2021", "name": "Yonaguni", "info": "Bad Bunny"},
{"year": "2021", "name": "Todo de Ti", "info": "Rauw Alejandro"},
{"year": "2021", "name": "We Didn't Have Much", "info": "Justin Moore"},
{"year": "2021", "name": "Drunk (And I Don't Wanna Go Home)", "info": "Elle King & Miranda Lambert"},
{"year": "2021", "name": "Wild Side", "info": "Normani Featuring Cardi B"},
{"year": "2021", "name": "You", "info": "Regard x Troye Sivan x Tate McRae"},
{"year": "2021", "name": "A-O-K", "info": "Tai Verdes"},
{"year": "2021", "name": "Love Again", "info": "Dua Lipa"},
{"year": "2021", "name": "Memory", "info": "Kane Brown X blackbear"},
{"year": "2021", "name": "I Was On A Boat That Day", "info": "Old Dominion"},
{"year": "2021", "name": "Don't Go Yet", "info": "Camila Cabello"},
{"year": "2021", "name": "SUVs (Black On Black)", "info": "Jack Harlow & Pooh Shiesty"},
{"year": "2021", "name": "Tombstone", "info": "Rod Wave"},
{"year": "2021", "name": "You Should Probably Leave", "info": "Chris Stapleton"},
{"year": "2021", "name": "My Boy", "info": "Elvie Shane"},
{"year": "2021", "name": "Come Through", "info": "H.E.R. Featuring Chris Brown"},
{"year": "2021", "name": "Straightenin", "info": "Migos"},
{"year": "2021", "name": "my.life", "info": "J. Cole, 21 Savage & Morray"},
{"year": "2021", "name": "Memory I Don't Mess With", "info": "Lee Brice"},
{"year": "2021", "name": "Blame It On You", "info": "Jason Aldean"},
{"year": "2021", "name": "Cold As You", "info": "Luke Combs"},
{"year": "2021", "name": "NDA", "info": "Billie Eilish"},
{"year": "2021", "name": "Gyalis", "info": "Capella Grey"},
{"year": "2021", "name": "EPMD 2", "info": "Nas Featuring Eminem & EPMD"},
{"year": "2021", "name": "Repeat It", "info": "Lil Tecca & Gunna"},
{"year": "2021", "name": "You Time", "info": "Scotty McCreery"},
{"year": "2021", "name": "Buy Dirt", "info": "Jordan Davis Featuring Luke Bryan"},
{"year": "2021", "name": "AM", "info": "Nio Garcia X J Balvin X Bad Bunny"},
{"year": "2021", "name": "Woman", "info": "Doja Cat"},
{"year": "2021", "name": "Over The Top", "info": "Smiley Featuring Drake"},
{"year": "2021", "name": "Lose", "info": "KSI x Lil Wayne"},
{"year": "2021", "name": "Hats Off", "info": "Lil Baby, Lil Durk & Travis Scott"},
{"year": "2021", "name": "I Hope Ur Miserable Until Ur Dead", "info": "Nessa Barrett"},
{"year": "2021", "name": "Favorite Crime", "info": "Olivia Rodrigo"},
{"year": "2021", "name": "Baddest", "info": "Yung Bleu, Chris Brown & 2 Chainz"},
{"year": "2021", "name": "Ball If I Want To", "info": "DaBaby"},
{"year": "2021", "name": "Not Sober", "info": "The Kid LAROI Featuring Polo G & Stunna Gambino"},
{"year": "2021", "name": "Knowing You", "info": "Kenny Chesney"},
{"year": "2021", "name": "WUSYANAME", "info": "Tyler, The Creator Featuring YoungBoy Never Broke Again & Ty Dolla $ign"},
{"year": "2021", "name": "Outside", "info": "MO3 X OG Bobby Billions"},
{"year": "2021", "name": "Next Girl", "info": "Carly Pearce"},
{"year": "2021", "name": "Happier", "info": "Olivia Rodrigo"},
{"year": "2021", "name": "Twerkulator", "info": "City Girls"},
{"year": "2021", "name": "Fiel", "info": "Los Legendarios, Wisin & Jhay Cortez"},
{"year": "2021", "name": "Rare", "info": "Nas"},
{"year": "2021", "name": "Rumors", "info": "Lizzo Featuring Cardi B"},
{"year": "2021", "name": "Paralyzed", "info": "Sueco"},
{"year": "2021", "name": "Get Into It (Yuh)", "info": "Doja Cat"},
{"year": "2021", "name": "Mind Of Melvin", "info": "YNW Melly Featuring Lil Uzi Vert"},
{"year": "2021", "name": "Papercuts", "info": "Machine Gun Kelly"},
{"year": "2021", "name": "Cold Heart (PNAU Remix)", "info": "Elton John & Dua Lipa"},
{"year": "2021", "name": "Brainwashed", "info": "Tom MacDonald"},
{"year": "2021", "name": "Thinking 'Bout You", "info": "Dustin Lynch Featuring Lauren Alaina Or MacKenzie Porter"},
{"year": "2021", "name": "I Like Dat", "info": "T-Pain & Kehlani"},
{"year": "2021", "name": "Steal My Love", "info": "Dan + Shay"},
{"year": "2021", "name": "5500 Degrees", "info": "EST Gee Featuring Lil Baby, 42 Dugg & Rylo Rodriguez"},
{"year": "2021", "name": "Summer Of Love", "info": "Shawn Mendes & Tainy"},
{"year": "2021", "name": "Matt Hardy 999", "info": "Trippie Redd Featuring Juice WRLD"},
{"year": "2021", "name": "Rich MF", "info": "Trippie Redd Featuring Lil Durk & Polo G"},
{"year": "2021", "name": "Already Won", "info": "Rod Wave Featuring Lil Durk"},
{"year": "2021", "name": "Betrayal", "info": "Trippie Redd Featuring Drake"},
{"year": "2021", "name": "Don't Go", "info": "Skrillex, Justin Bieber & Don Toliver"},
{"year": "2021", "name": "One Mississippi", "info": "Kane Brown"},
{"year": "2021", "name": "Visiting Hours", "info": "Ed Sheeran"},
{"year": "2021", "name": "Holy Smokes", "info": "Trippie Redd Featuring Lil Uzi Vert"},
{"year": "2021", "name": "Miss The Rage", "info": "Trippie Redd & Playboi Carti"},
{"year": "2021", "name": "MP5", "info": "Trippie Redd Featuring SoFaygo"},
{"year": "2021", "name": "Brutal", "info": "Olivia Rodrigo"},
{"year": "2021", "name": "I Guess I'm In Love", "info": "Clinton Kane"},
{"year": "2021", "name": "Get Ready", "info": "Rod Wave Featuring Kodak Black"},
{"year": "2021", "name": "Danny Phantom", "info": "Trippie Redd Featuring XXXTENTACION"},
{"year": "2021", "name": "What's Wrong", "info": "Rod Wave"},
{"year": "2021", "name": "Demon Time", "info": "Trippie Redd Featuring Ski Mask The Slump God"},
{"year": "2021", "name": "Tick Tock", "info": "Young Thug"},
{"year": "2021", "name": "Time Heals", "info": "Rod Wave"},
{"year": "2021", "name": "Hurricane", "info": "Kanye West"},
{"year": "2021", "name": "Jail", "info": "Kanye West"},
{"year": "2021", "name": "Off The Grid", "info": "Kanye West"},
{"year": "2021", "name": "Ok Ok", "info": "Kanye West"},
{"year": "2021", "name": "Junya", "info": "Kanye West"},
{"year": "2021", "name": "Moon", "info": "Kanye West"},
{"year": "2021", "name": "Family Ties", "info": "Baby Keem & Kendrick Lamar"},
{"year": "2021", "name": "Praise God", "info": "Kanye West"},
{"year": "2021", "name": "Sharing Locations", "info": "Meek Mill Featuring Lil Baby & Lil Durk"},
{"year": "2021", "name": "Jesus Lord", "info": "Kanye West"},
{"year": "2021", "name": "Jonah", "info": "Kanye West"},
{"year": "2021", "name": "Believe What I Say", "info": "Kanye West"},
{"year": "2021", "name": "God Breathed", "info": "Kanye West"},
{"year": "2021", "name": "Remote Control", "info": "Kanye West"},
{"year": "2021", "name": "Heaven And Hell", "info": "Kanye West"},
{"year": "2021", "name": "24", "info": "Kanye West"},
{"year": "2021", "name": "Pure Souls", "info": "Kanye West"},
{"year": "2021", "name": "No Child Left Behind", "info": "Kanye West"},
{"year": "2021", "name": "Donda", "info": "Kanye West"},
{"year": "2021", "name": "Keep My Spirit Alive", "info": "Kanye West"},
{"year": "2021", "name": "Jail Pt 2", "info": "Kanye West"},
{"year": "2021", "name": "I Am Not A Woman, I'm A God", "info": "Halsey"},
{"year": "2021", "name": "New Again", "info": "Kanye West"},
{"year": "2021", "name": "Lord I Need You", "info": "Kanye West"},
{"year": "2021", "name": "Come To Life", "info": "Kanye West"},
{"year": "2021", "name": "Tell The Vision", "info": "Kanye West"},
{"year": "2021", "name": "In Da Getto", "info": "J Balvin & Skrillex"},
{"year": "2021", "name": "Way 2 Sexy", "info": "Drake Featuring Future & Young Thug"},
{"year": "2021", "name": "Girls Want Girls", "info": "Drake Featuring Lil Baby"},
{"year": "2021", "name": "Fair Trade", "info": "Drake Featuring Travis Scott"},
{"year": "2021", "name": "Champagne Poetry", "info": "Drake"},
{"year": "2021", "name": "Knife Talk", "info": "Drake Featuring 21 Savage & Project Pat"},
{"year": "2021", "name": "In The Bible", "info": "Drake Featuring Lil Durk & Giveon"},
{"year": "2021", "name": "Papi's Home", "info": "Drake"},
{"year": "2021", "name": "TSU", "info": "Drake"},
{"year": "2021", "name": "Love All", "info": "Drake Featuring JAY-Z"},
{"year": "2021", "name": "No Friends In The Industry", "info": "Drake"},
{"year": "2021", "name": "N 2 Deep", "info": "Drake Featuring Future"},
{"year": "2021", "name": "Pipe Down", "info": "Drake"},
{"year": "2021", "name": "7am On Bridle Path", "info": "Drake"},
{"year": "2021", "name": "Race My Mind", "info": "Drake"},
{"year": "2021", "name": "IMY2", "info": "Drake Featuring Kid Cudi"},
{"year": "2021", "name": "Yebba's Heartbreak", "info": "Drake & Yebba"},
{"year": "2021", "name": "You Only Live Twice", "info": "Drake Featuring Lil Wayne & Rick Ross"},
{"year": "2021", "name": "Fountains", "info": "Drake Featuring Tems"},
{"year": "2021", "name": "Get Along Better", "info": "Drake Featuring Ty Dolla $ign"},
{"year": "2021", "name": "Fucking Fans", "info": "Drake"},
{"year": "2021", "name": "The Remorse", "info": "Drake"},
{"year": "2021", "name": "Blue Note$ II", "info": "Meek Mill Featuring Lil Uzi Vert"},
{"year": "2021", "name": "Shivers", "info": "Ed Sheeran"},
{"year": "2021", "name": "Have Mercy", "info": "Chloe"},
{"year": "2021", "name": "Range Brothers", "info": "Baby Keem & Kendrick Lamar"},
{"year": "2021", "name": "Life Support", "info": "YoungBoy Never Broke Again"},
{"year": "2021", "name": "Meet Me At Our Spot", "info": "THE ANXIETY: WILLOW & Tyler Cole"},
{"year": "2021", "name": "Lonely", "info": "DaBaby X Lil Wayne"},
{"year": "2021", "name": "Lalisa", "info": "Lisa"},
{"year": "2021", "name": "Thats What I Want", "info": "Lil Nas X"},
{"year": "2021", "name": "Wildest Dreams (Taylor's Version)", "info": "Taylor Swift"},
{"year": "2021", "name": "Scoop", "info": "Lil Nas X Featuring Doja Cat"},
{"year": "2021", "name": "Dolla Sign Slime", "info": "Lil Nas X Featuring Megan Thee Stallion"},
{"year": "2021", "name": "On My Side", "info": "YoungBoy Never Broke Again"},
{"year": "2021", "name": "Dead Right Now", "info": "Lil Nas X"},
{"year": "2021", "name": "Love Nwantiti (Ah Ah Ah)", "info": "CKay"},
{"year": "2021", "name": "Tales Of Dominica", "info": "Lil Nas X"},
{"year": "2021", "name": "One Of Me", "info": "Lil Nas X Featuring Elton John"},
{"year": "2021", "name": "Lost In The Citadel", "info": "Lil Nas X"},
{"year": "2021", "name": "Sun Goes Down", "info": "Lil Nas X"},
{"year": "2021", "name": "Am I Dreaming", "info": "Lil Nas X Featuring Miley Cyrus"},
{"year": "2021", "name": "Same Boat", "info": "Zac Brown Band"},
{"year": "2021", "name": "My Universe", "info": "Coldplay x BTS"},
{"year": "2021", "name": "Bad Morning", "info": "YoungBoy Never Broke Again"},
{"year": "2021", "name": "Your Heart", "info": "Joyner Lucas & J. Cole"},
{"year": "2021", "name": "Too Easy", "info": "Gunna & Future"},
{"year": "2021", "name": "No Where", "info": "YoungBoy Never Broke Again"},
{"year": "2021", "name": "Hold Me Down", "info": "YoungBoy Never Broke Again"},
{"year": "2021", "name": "Nevada", "info": "YoungBoy Never Broke Again"},
{"year": "2021", "name": "50 Shots", "info": "YoungBoy Never Broke Again"},
{"year": "2021", "name": "Smoke Strong", "info": "YoungBoy Never Broke Again"},
{"year": "2021", "name": "Break Or Make Me", "info": "YoungBoy Never Broke Again"},
{"year": "2021", "name": "Sincerely", "info": "YoungBoy Never Broke Again"},
{"year": "2021", "name": "I Can't Take It Back", "info": "YoungBoy Never Broke Again"},
{"year": "2021", "name": "Forgiato", "info": "YoungBoy Never Broke Again"},
{"year": "2021", "name": "Rich Shit", "info": "YoungBoy Never Broke Again"},
{"year": "2021", "name": "For Tonight", "info": "Giveon"},
{"year": "2021", "name": "Baddest Thing", "info": "YoungBoy Never Broke Again"},
{"year": "2021", "name": "Chosen", "info": "Blxst & Tyga Featuring Ty Dolla $ign"},
{"year": "2021", "name": "Toxic Punk", "info": "YoungBoy Never Broke Again"},
{"year": "2021", "name": "Intro (Hate On Me)", "info": "Meek Mill"},
{"year": "2021", "name": "Hot", "info": "Meek Mill Featuring Moneybagg Yo"},
{"year": "2021", "name": "Expensive Pain", "info": "Meek Mill"},
{"year": "2021", "name": "On My Soul", "info": "Meek Mill"},
{"year": "2021", "name": "Jugaste y Sufri", "info": "Eslabon Armado Featuring DannyLux"},
{"year": "2021", "name": "Outside (100 MPH)", "info": "Meek Mill"},
{"year": "2021", "name": "Last One Standing", "info": "Skylar Grey, Polo G, Mozzy & Eminem"},
{"year": "2021", "name": "The Feels", "info": "TWICE"},
{"year": "2021", "name": "Me (FWM)", "info": "Meek Mill Featuring A$AP Ferg"},
{"year": "2021", "name": "Love Train", "info": "Meek Mill"},
{"year": "2021", "name": "Feelin Like Tunechi", "info": "Lil Wayne Featuring Rich The Kid"},
{"year": "2021", "name": "Ghost", "info": "Justin Bieber"},
{"year": "2021", "name": "Sand In My Boots", "info": "Morgan Wallen"},
{"year": "2021", "name": "Ride For You", "info": "Meek Mill Featuring Kehlani"},
{"year": "2021", "name": "Esta Danada", "info": "Ivan Cornejo"},
{"year": "2021", "name": "Whiskey And Rain", "info": "Michael Ray"},
{"year": "2021", "name": "Who Want Smoke??", "info": "Nardo Wick Featuring G Herbo, Lil Durk & 21 Savage"},
{"year": "2021", "name": "Lo Siento BB:/", "info": "Tainy, Bad Bunny & Julieta Venegas"},
{"year": "2021", "name": "Flocky Flocky", "info": "Don Toliver Featuring Travis Scott"},
{"year": "2021", "name": "Easy On Me", "info": "Adele"},
{"year": "2021", "name": "WFM", "info": "RealestK"},
{"year": "2021", "name": "Maybach", "info": "42 Dugg Featuring Future"},
{"year": "2021", "name": "Tequila Little Time", "info": "Jon Pardi"},
{"year": "2021", "name": "Freedom Was A Highway", "info": "Jimmie Allen & Brad Paisley"},
{"year": "2021", "name": "Like A Lady", "info": "Lady A"},
{"year": "2021", "name": "Life Goes On", "info": "Oliver Tree"},
{"year": "2021", "name": "Woo Baby", "info": "Pop Smoke Featuring Chris Brown"},
{"year": "2021", "name": "'Til You Can't", "info": "Cody Johnson"},
{"year": "2021", "name": "Who's In Your Head", "info": "Jonas Brothers"},
{"year": "2021", "name": "Just About Over You", "info": "Priscilla Block"},
{"year": "2021", "name": "Bubbly", "info": "Young Thug With Drake & Travis Scott"},
{"year": "2021", "name": "Pissed Me Off", "info": "Lil Durk"},
{"year": "2021", "name": "Lets Go Brandon", "info": "Loza Alexander"},
{"year": "2021", "name": "Ex For A Reason", "info": "Summer Walker & JT"},
{"year": "2021", "name": "Better Days", "info": "NEIKED X Mae Muller X Polo G"},
{"year": "2021", "name": "Livin It Up", "info": "Young Thug With Post Malone & A$AP Rocky"},
{"year": "2021", "name": "Stressed", "info": "Young Thug With J. Cole & T-Shyne"},
{"year": "2021", "name": "Rich N***a Shit", "info": "Young Thug With Juice WRLD"},
{"year": "2021", "name": "Let Somebody Go", "info": "Coldplay X Selena Gomez"},
{"year": "2021", "name": "Ya Superame (En Vivo Desde Culiacan, Sinaloa)", "info": "Grupo Firme"},
{"year": "2021", "name": "Peepin Out The Window", "info": "Young Thug With Future & BSlime"},
{"year": "2021", "name": "Moth To A Flame", "info": "Swedish House Mafia & The Weeknd"},
{"year": "2021", "name": "Let's Go Brandon", "info": "Bryson Gray Featuring Tyson James & Chandler Crump"},
{"year": "2021", "name": "Not In The Mood", "info": "Lil Tjay, Fivio Foreign & Kay Flock"},
{"year": "2021", "name": "Switches & Dracs", "info": "Moneybagg Yo Featuring Lil Durk & EST Gee"},
{"year": "2021", "name": "Poke It Out", "info": "Wale Featuring J. Cole"},
{"year": "2021", "name": "Scorpio", "info": "Moneybagg Yo"},
{"year": "2021", "name": "Big Energy", "info": "Latto"},
{"year": "2021", "name": "Half Of My Hometown", "info": "Kelsea Ballerini Featuring Kenny Chesney"},
{"year": "2021", "name": "Money", "info": "Lisa"},
{"year": "2021", "name": "To Be Loved By You", "info": "Parker McCollum"},
{"year": "2021", "name": "Thriller", "info": "Michael Jackson"},
{"year": "2021", "name": "Monster Mash", "info": "Bobby \"Boris\" Pickett And The Crypt-Kickers"},
{"year": "2021", "name": "Ghostbusters", "info": "Ray Parker Jr."},
{"year": "2021", "name": "Overpass Graffiti", "info": "Ed Sheeran"},
{"year": "2021", "name": "Somebody's Watching Me", "info": "Rockwell"},
{"year": "2021", "name": "Demon High", "info": "Lil Uzi Vert"},
{"year": "2021", "name": "Rap Freaks", "info": "Yung Miami"},
{"year": "2021", "name": "Eat It", "info": "Megan Thee Stallion"},
{"year": "2021", "name": "Ghost Town", "info": "Benson Boone"},
{"year": "2021", "name": "One Right Now", "info": "Post Malone & The Weeknd"},
{"year": "2021", "name": "Smokin Out The Window", "info": "Silk Sonic (Bruno Mars & Anderson .Paak)"},
{"year": "2021", "name": "Escape Plan", "info": "Travis Scott"},
{"year": "2021", "name": "No Love", "info": "Summer Walker & SZA"},
{"year": "2021", "name": "Bitter", "info": "Summer Walker & Cardi B"},
{"year": "2021", "name": "Mafia", "info": "Travis Scott"},
{"year": "2021", "name": "Throw It Away", "info": "Summer Walker"},
{"year": "2021", "name": "Reciprocate", "info": "Summer Walker"},
{"year": "2021", "name": "Toxic", "info": "Summer Walker Featuring Lil Durk"},
{"year": "2021", "name": "Unloyal", "info": "Summer Walker & Ari Lennox"},
{"year": "2021", "name": "Constant Bulls**t", "info": "Summer Walker"},
{"year": "2021", "name": "You Don't Know Me", "info": "Summer Walker"},
{"year": "2021", "name": "Insane", "info": "Summer Walker"},
{"year": "2021", "name": "Circus", "info": "Summer Walker"},
{"year": "2021", "name": "4th Baby Mama", "info": "Summer Walker"},
{"year": "2021", "name": "Switch A N*gga Out", "info": "Summer Walker"},
{"year": "2021", "name": "Closure", "info": "Summer Walker"},
{"year": "2021", "name": "Session 33", "info": "Summer Walker"},
{"year": "2021", "name": "Screwin", "info": "Summer Walker & Omarion"},
{"year": "2021", "name": "Broken Promises", "info": "Summer Walker"},
{"year": "2021", "name": "Dat Right There", "info": "Summer Walker, Pharrell Williams & The Neptunes"},
{"year": "2021", "name": "Sad Girlz Luv Money", "info": "Amaarae & Moliy Featuring Kali Uchis"},
{"year": "2021", "name": "Slow Down Summer", "info": "Thomas Rhett"},
{"year": "2021", "name": "Jumpin", "info": "NLE Choppa Featuring Polo G"},
{"year": "2021", "name": "Super Gremlin", "info": "Kodak Black"},
{"year": "2021", "name": "All Too Well (Taylor's Version)", "info": "Taylor Swift"},
{"year": "2021", "name": "State Of Grace (Taylor's Version)", "info": "Taylor Swift"},
{"year": "2021", "name": "Already Dead", "info": "Juice WRLD"},
{"year": "2021", "name": "I Bet You Think About Me (Taylor's Version) (From The Vault)", "info": "Taylor Swift Featuring Chris Stapleton"},
{"year": "2021", "name": "Red (Taylor's Version)", "info": "Taylor Swift"},
{"year": "2021", "name": "All I Want For Christmas Is You", "info": "Mariah Carey"},
{"year": "2021", "name": "Nothing New (Taylor's Version) (From The Vault)", "info": "Taylor Swift Featuring Phoebe Bridgers"},
{"year": "2021", "name": "Message In A Bottle (Taylor's Version) (From The Vault)", "info": "Taylor Swift"},
{"year": "2021", "name": "I Knew You Were Trouble (Taylor's Version)", "info": "Taylor Swift"},
{"year": "2021", "name": "Run (Taylor's Version) (From The Vault)", "info": "Taylor Swift Featuring Ed Sheeran"},
{"year": "2021", "name": "Bad Man (Smooth Criminal)", "info": "Polo G"},
{"year": "2021", "name": "Better Man (Taylor's Version) (From The Vault)", "info": "Taylor Swift"},
{"year": "2021", "name": "22 (Taylor's Version)", "info": "Taylor Swift"},
{"year": "2021", "name": "Doin' This", "info": "Luke Combs"},
{"year": "2021", "name": "Treacherous (Taylor's Version)", "info": "Taylor Swift"},
{"year": "2021", "name": "We Are Never Ever Getting Back Together (Taylor's Version)", "info": "Taylor Swift"},
{"year": "2021", "name": "I Almost Do (Taylor's Version)", "info": "Taylor Swift"},
{"year": "2021", "name": "The Very First Night (Taylor's Version) (From The Vault)", "info": "Taylor Swift"},
{"year": "2021", "name": "Everything Has Changed (Taylor's Version)", "info": "Taylor Swift Featuring Ed Sheeran"},
{"year": "2021", "name": "The Last Time (Taylor's Version)", "info": "Taylor Swift Featuring Gary Lightbody Of Snow Patrol"},
{"year": "2021", "name": "Stay Stay Stay (Taylor's Version)", "info": "Taylor Swift"},
{"year": "2021", "name": "After Last Night", "info": "Silk Sonic (Bruno Mars & Anderson .Paak) With Thundercat & Bootsy Collins"},
{"year": "2021", "name": "Babe (Taylor's Version) (From The Vault)", "info": "Taylor Swift"},
{"year": "2021", "name": "Blast Off", "info": "Silk Sonic (Bruno Mars & Anderson .Paak)"},
{"year": "2021", "name": "Holy Ground (Taylor's Version)", "info": "Taylor Swift"},
{"year": "2021", "name": "Begin Again (Taylor's Version)", "info": "Taylor Swift"},
{"year": "2021", "name": "Put On A Smile", "info": "Silk Sonic (Bruno Mars & Anderson .Paak)"},
{"year": "2021", "name": "Forever Winter (Taylor's Version) (From The Vault)", "info": "Taylor Swift"},
{"year": "2021", "name": "Fly As Me", "info": "Silk Sonic (Bruno Mars & Anderson .Paak)"},
{"year": "2021", "name": "The Moment I Knew (Taylor's Version)", "info": "Taylor Swift"},
{"year": "2021", "name": "The Lucky One (Taylor's Version)", "info": "Taylor Swift"},
{"year": "2021", "name": "Sad Beautiful Tragic (Taylor's Version)", "info": "Taylor Swift"},
{"year": "2021", "name": "Come Back...Be Here (Taylor's Version)", "info": "Taylor Swift"},
{"year": "2021", "name": "Starlight (Taylor's Version)", "info": "Taylor Swift"},
{"year": "2021", "name": "La Fama", "info": "Rosalia Featuring The Weeknd"},
{"year": "2021", "name": "Oh My God", "info": "Adele"},
{"year": "2021", "name": "Rockin' Around The Christmas Tree", "info": "Brenda Lee"},
{"year": "2021", "name": "I Drink Wine", "info": "Adele"},
{"year": "2021", "name": "Jingle Bell Rock", "info": "Bobby Helms"},
{"year": "2021", "name": "My Little Love", "info": "Adele"},
{"year": "2021", "name": "Can I Get It", "info": "Adele"},
{"year": "2021", "name": "A Holly Jolly Christmas", "info": "Burl Ives"},
{"year": "2021", "name": "It's The Most Wonderful Time Of The Year", "info": "Andy Williams"},
{"year": "2021", "name": "To Be Loved", "info": "Adele"},
{"year": "2021", "name": "Last Christmas", "info": "Wham!"},
{"year": "2021", "name": "Strangers By Nature", "info": "Adele"},
{"year": "2021", "name": "Cry Your Heart Out", "info": "Adele"},
{"year": "2021", "name": "Hold On", "info": "Adele"},
{"year": "2021", "name": "abcdefu", "info": "GAYLE"},
{"year": "2021", "name": "All Night Parking (Interlude)", "info": "Adele With Erroll Garner"},
{"year": "2021", "name": "Woman Like Me", "info": "Adele"},
{"year": "2021", "name": "Love Is A Game", "info": "Adele"},
{"year": "2021", "name": "God's Country", "info": "State Of Mine & Drew Jacobs"},
{"year": "2021", "name": "Enemy", "info": "Imagine Dragons X JID"},
{"year": "2021", "name": "Heart On Fire", "info": "Eric Church"},
{"year": "2021", "name": "Feliz Navidad", "info": "Jose Feliciano"},
{"year": "2021", "name": "Christmas (Baby Please Come Home)", "info": "Darlene Love"},
{"year": "2021", "name": "The Christmas Song (Merry Christmas To You)", "info": "Nat King Cole"},
{"year": "2021", "name": "Sleigh Ride", "info": "The Ronettes"},
{"year": "2021", "name": "It's Beginning To Look A Lot Like Christmas", "info": "Michael Buble"},
{"year": "2021", "name": "Let It Snow, Let It Snow, Let It Snow", "info": "Dean Martin"},
{"year": "2021", "name": "White Christmas", "info": "Bing Crosby"},
{"year": "2021", "name": "Underneath The Tree", "info": "Kelly Clarkson"},
{"year": "2021", "name": "Happy Holiday / The Holiday Season", "info": "Andy Williams"},
{"year": "2021", "name": "Rudolph The Red-Nosed Reindeer", "info": "Gene Autry"},
{"year": "2021", "name": "Santa Tell Me", "info": "Ariana Grande"},
{"year": "2021", "name": "Run Rudolph Run", "info": "Chuck Berry"},
{"year": "2021", "name": "(There's No Place Like) Home For The Holidays", "info": "Perry Como"},
{"year": "2021", "name": "By Your Side", "info": "Rod Wave"},
{"year": "2021", "name": "Pick Out A Christmas Tree", "info": "Dan + Shay"},
{"year": "2021", "name": "Christmas Tree Farm (Old Timey Version)", "info": "Taylor Swift"},
{"year": "2021", "name": "Always Been You", "info": "Jessie Murph"},
{"year": "2021", "name": "I Hate U", "info": "SZA"},
{"year": "2021", "name": "It's Beginning To Look A Lot Like Christmas", "info": "Perry Como And The Fontane Sisters With Mitchell Ayres And His Orchestra"},
{"year": "2021", "name": "Wandered To LA.", "info": "Juice WRLD & Justin Bieber"},
{"year": "2021", "name": "Don't Play", "info": "Polo G Featuring Lil Baby"},
{"year": "2021", "name": "Merry Christmas", "info": "Ed Sheeran & Elton John"},
{"year": "2021", "name": "Me Or Sum", "info": "Nardo Wick, Lil Baby & Future"},
{"year": "2021", "name": "Young N Dumb", "info": "Polo G"},
{"year": "2021", "name": "Start Up Again", "info": "Polo G Featuring Moneybagg Yo"},
{"year": "2021", "name": "I'll Be Home For Christmas", "info": "Camila Cabello"},
{"year": "2021", "name": "Mercedes", "info": "Brent Faiyaz"},
{"year": "2021", "name": "Partin Ways", "info": "Polo G"},
{"year": "2021", "name": "Girl Of My Dreams", "info": "Juice WRLD & SUGA"},
{"year": "2021", "name": "Burn", "info": "Juice WRLD"},
{"year": "2021", "name": "Wonderful Christmastime", "info": "Paul McCartney"},
{"year": "2021", "name": "You're A Mean One, Mr. Grinch", "info": "Thurl Ravenscroft"},
{"year": "2021", "name": "Mistletoe", "info": "Justin Bieber"},
{"year": "2021", "name": "Santa Baby", "info": "Eartha Kitt With Henri Rene And His Orchestra"},
{"year": "2021", "name": "Feline", "info": "Juice WRLD, Polo G & Trippie Redd"},
{"year": "2021", "name": "Rockstar In His Prime", "info": "Juice WRLD"},
{"year": "2021", "name": "You Wouldn't Understand", "info": "Juice WRLD"},
{"year": "2021", "name": "Doom", "info": "Juice WRLD"},
{"year": "2021", "name": "Go Hard", "info": "Juice WRLD"},
{"year": "2021", "name": "Not Enough", "info": "Juice WRLD"},
{"year": "2021", "name": "Man In The Mirror", "info": "A Boogie Wit da Hoodie"},
{"year": "2021", "name": "From My Window", "info": "Juice WRLD"},
{"year": "2021", "name": "Relocate", "info": "Juice WRLD"},
{"year": "2021", "name": "Feel Alone", "info": "Juice WRLD"}
]
